airflow/providers/apache/kafka/__init__.py
airflow/providers/apache/kafka/get_provider_info.py
airflow/providers/apache/kafka/version_compat.py
airflow/providers/apache/kafka/hooks/__init__.py
airflow/providers/apache/kafka/hooks/base.py
airflow/providers/apache/kafka/hooks/client.py
airflow/providers/apache/kafka/hooks/consume.py
airflow/providers/apache/kafka/hooks/produce.py
airflow/providers/apache/kafka/operators/__init__.py
airflow/providers/apache/kafka/operators/consume.py
airflow/providers/apache/kafka/operators/produce.py
airflow/providers/apache/kafka/queues/__init__.py
airflow/providers/apache/kafka/queues/kafka.py
airflow/providers/apache/kafka/sensors/__init__.py
airflow/providers/apache/kafka/sensors/kafka.py
airflow/providers/apache/kafka/triggers/__init__.py
airflow/providers/apache/kafka/triggers/await_message.py
airflow/providers/apache/kafka/triggers/msg_queue.py
apache_airflow_providers_apache_kafka-1.11.3.dist-info/entry_points.txt
apache_airflow_providers_apache_kafka-1.11.3.dist-info/licenses/LICENSE
apache_airflow_providers_apache_kafka-1.11.3.dist-info/licenses/NOTICE
apache_airflow_providers_apache_kafka-1.11.3.dist-info/WHEEL
apache_airflow_providers_apache_kafka-1.11.3.dist-info/METADATA
apache_airflow_providers_apache_kafka-1.11.3.dist-info/RECORD
